bluesearch/__init__.py
bluesearch/embedding_models.py
bluesearch/py.typed
bluesearch/search.py
bluesearch/sql.py
bluesearch/utils.py
bluesearch/version.py
bluesearch/_css/__init__.py
bluesearch/_css/style.py
bluesearch/_css/stylesheet.css
bluesearch/database/__init__.py
bluesearch/database/article.py
bluesearch/database/cord_19.py
bluesearch/database/mining_cache.py
bluesearch/entrypoint/__init__.py
bluesearch/entrypoint/_helper.py
bluesearch/entrypoint/compute_embeddings.py
bluesearch/entrypoint/create_database.py
bluesearch/entrypoint/create_mining_cache.py
bluesearch/entrypoint/embedding_server.py
bluesearch/entrypoint/mining_server.py
bluesearch/entrypoint/search_server.py
bluesearch/mining/__init__.py
bluesearch/mining/attribute.py
bluesearch/mining/entity.py
bluesearch/mining/eval.py
bluesearch/mining/pipeline.py
bluesearch/mining/relation.py
bluesearch/server/__init__.py
bluesearch/server/embedding_server.py
bluesearch/server/invalid_usage_exception.py
bluesearch/server/mining_server.py
bluesearch/server/search_server.py
bluesearch/widgets/__init__.py
bluesearch/widgets/article_saver.py
bluesearch/widgets/mining_schema.py
bluesearch/widgets/mining_widget.py
bluesearch/widgets/search_widget.py
bluesearch-0.2.0.dist-info/AUTHORS.md
bluesearch-0.2.0.dist-info/COPYING
bluesearch-0.2.0.dist-info/COPYING.LESSER
bluesearch-0.2.0.dist-info/METADATA
bluesearch-0.2.0.dist-info/WHEEL
bluesearch-0.2.0.dist-info/entry_points.txt
bluesearch-0.2.0.dist-info/top_level.txt
bluesearch-0.2.0.dist-info/RECORD
