Metadata-Version: 2.1
Name: bluesearch
Version: 0.2.0
Summary: Blue Brain text mining toolbox for semantic search and information extraction
Home-page: https://github.com/BlueBrain/Search
Author: Blue Brain Project, EPFL
License: -
Download-URL: https://pypi.python.org/pypi/bluesearch
Project-URL: Source, https://github.com/BlueBrain/Search
Project-URL: Documentation, https://blue-brain-search.readthedocs.io/en/stable/
Project-URL: Tracker, https://github.com/BlueBrain/Search/issues
Platform: UNKNOWN
Classifier: Development Status :: 4 - Beta
Classifier: License :: OSI Approved :: GNU Lesser General Public License v3 (LGPLv3)
Classifier: Operating System :: Unix
Classifier: Operating System :: MacOS
Classifier: Programming Language :: Python
Classifier: Programming Language :: Python :: 3
Classifier: Programming Language :: Python :: 3.7
Classifier: Programming Language :: Python :: 3.8
Classifier: Programming Language :: Python :: 3.9
Classifier: Programming Language :: Python :: 3 :: Only
Classifier: Topic :: Scientific/Engineering :: Artificial Intelligence
Classifier: Topic :: Software Development :: Libraries :: Python Modules
Classifier: Topic :: Text Processing :: General
Requires-Python: >=3.7
License-File: COPYING
License-File: COPYING.LESSER
License-File: AUTHORS.md
Requires-Dist: Flask
Requires-Dist: SQLAlchemy[mysql,pymysql]
Requires-Dist: catalogue (>=2.0.3)
Requires-Dist: cryptography (>=3.2)
Requires-Dist: h5py
Requires-Dist: ipython
Requires-Dist: ipywidgets
Requires-Dist: jupyterlab (>=3)
Requires-Dist: langdetect
Requires-Dist: numpy (>=1.20.1)
Requires-Dist: pandas (>=1)
Requires-Dist: python-dotenv
Requires-Dist: requests
Requires-Dist: scikit-learn
Requires-Dist: sentence-transformers
Requires-Dist: spacy[transformers] (>=3.0.6)
Requires-Dist: torch
Provides-Extra: data_and_models
Requires-Dist: PyYAML ; extra == 'data_and_models'
Requires-Dist: dvc[ssh] (>=2) ; extra == 'data_and_models'
Requires-Dist: matplotlib ; extra == 'data_and_models'
Requires-Dist: scipy ; extra == 'data_and_models'
Requires-Dist: transformers ; extra == 'data_and_models'
Requires-Dist: spacy-lookups-data ; extra == 'data_and_models'
Requires-Dist: srsly ; extra == 'data_and_models'
Requires-Dist: typer ; extra == 'data_and_models'
Provides-Extra: dev
Requires-Dist: Sphinx ; extra == 'dev'
Requires-Dist: docker ; extra == 'dev'
Requires-Dist: pytest-benchmark ; extra == 'dev'
Requires-Dist: pytest-cov ; extra == 'dev'
Requires-Dist: pytest (>=4.6) ; extra == 'dev'
Requires-Dist: responses ; extra == 'dev'
Requires-Dist: sphinx-bluebrain-theme ; extra == 'dev'
Requires-Dist: tox ; extra == 'dev'
